LICENSE
README.md
setup.cfg
setup.py
pyportall/__init__.py
pyportall/exceptions.py
pyportall/utils.py
pyportall.egg-info/PKG-INFO
pyportall.egg-info/SOURCES.txt
pyportall.egg-info/dependency_links.txt
pyportall.egg-info/requires.txt
pyportall.egg-info/top_level.txt
pyportall/api/__init__.py
pyportall/api/engine/__init__.py
pyportall/api/engine/core.py
pyportall/api/engine/geopandas.py
pyportall/api/engine/metadata.py
pyportall/api/models/__init__.py
pyportall/api/models/geojson.py
pyportall/api/models/geopandas.py
pyportall/api/models/indicators.py
pyportall/api/models/lbs.py
pyportall/api/models/metadata.py
pyportall/api/models/preflight.py