Metadata-Version: 2.1
Name: pyportall
Version: 0.0.9
Summary: Portall Python SDK
Home-page: UNKNOWN
Author: Daniel Carrión
Author-email: dcarrion@inspide.com
License: MIT
Platform: UNKNOWN
Classifier: Programming Language :: Python :: 3.8
Classifier: Programming Language :: Python :: 3.9
Classifier: License :: Other/Proprietary License
Classifier: Operating System :: OS Independent
License-File: LICENSE
